{
  "name": "炎_グレンアルマ_加速_V6_純正_サブ0枚",
  "strategy": "combo",
  "win_rate": 0.34766763848396504,
  "wins": 7155,
  "total_games": 20580,
  "deck_composition": [
    "ウインディex",
    "エースバーン",
    "カルボウ",
    "グレンアルマex",
    "バクガメス",
    "ヒヒダルマ",
    "ファイヤーex",
    "マルヤクデ",
    "メガバシャーモex",
    "ヤトウモリ",
    "かんこうきゃく",
    "ふしぎなアメ",
    "ふしぎなアメ",
    "ふたの化石",
    "アカネ",
    "カキ",
    "キョウ",
    "スイレン",
    "当たりつきアイス",
    "旅の行商人"
  ],
  "mutation_history": [
    {
      "gen": 0,
      "diff": "Initial construction"
    },
    {
      "gen": 15,
      "diff": "Out: ワカシャモ / In: ウインディex (Parent: 26/50 -> Mutant: 28/50)"
    },
    {
      "gen": 21,
      "diff": "Out: ヒトモシ / In: ヒヒダルマ (Parent: 24/50 -> Mutant: 31/50)"
    },
    {
      "gen": 47,
      "diff": "Out: ポケモンセンターのお姉さん / In: カルボウ (Parent: 19/50 -> Mutant: 22/50)"
    },
    {
      "gen": 100,
      "diff": "Out: ひみつのコハク / In: オドリドリ (Parent: 21/50 -> Mutant: 27/50)"
    },
    {
      "gen": 105,
      "diff": "Out: オドリドリ / In: 当たりつきアイス (Parent: 21/50 -> Mutant: 25/50)"
    },
    {
      "gen": 139,
      "diff": "Out: グレンアルマex / In: ファイヤーex (Parent: 15/50 -> Mutant: 24/50)"
    }
  ]
}