{
  "title": "フェリシモ、EC用お届け袋で資源2.5トン削減 - LOGISTICS TODAY",
  "link": "https://news.google.com/rss/articles/CBMiSEFVX3lxTE9ySlpjY1VPQXRfWDdkdGc0NGpGdFg2b0xkLTVuMzBwVXdrcEFNZ1hGOGpSYXZRRHU1eHdfQkNKV2JsSGhwSmNkZw?oc=5",
  "raw_summary": "<a href=\"https://news.google.com/rss/articles/CBMiSEFVX3lxTE9ySlpjY1VPQXRfWDdkdGc0NGpGdFg2b0xkLTVuMzBwVXdrcEFNZ1hGOGpSYXZRRHU1eHdfQkNKV2JsSGhwSmNkZw?oc=5\" target=\"_blank\">フェリシモ、EC用お届け袋で資源2.5トン削減</a>&nbsp;&nbsp;<font color=\"#6f6f6f\">LOGISTICS TODAY</font>",
  "ai_analysis": {
    "strength": "環境意識の高さ、サプライチェーンにおける環境負荷低減への取り組み、企業イメージ向上、顧客ロイヤリティ向上。",
    "weakness": "削減量の少なさ（2.5トンは企業規模に対して微量）、コスト増の可能性、環境負荷低減以外の競争力（価格、品質など）への影響。",
    "opportunity": "環境意識の高い企業への就職意欲をアピールできる。サプライチェーンの持続可能性、環境経営に関する知識を深めるチャンス。",
    "threat": "他社も同様の取り組みを推進しており、差別化が難しくなる可能性。グリーンウォッシュ（見せかけの環境対策）と批判されるリスク。"
  },
  "critical_analysis": {},
  "deep_strategic_dossier": "",
  "bias": "",
  "collected_at": "2026-01-28T13:34:11.835706",
  "source": "フェリシモ 採用",
  "score": 5
}