{
  "title": "漫画「電子版」5年で2.7倍の急成長、コミック販売7000億",
  "link": "https://news.google.com/rss/articles/CBMiX0FVX3lxTE5ZbXg3RWZ1RldrS3NoaFZWYXN2NEtUcHRGUll0dXhhQTBhNUZHTE9fLWQwRmRCTE0zTVZocGV0UTZ1M1BtQ3FKTlJfRWJoeFREOURWb1ZEQ3ZJZHNlelBv?oc=5",
  "raw_summary": "<a href=\"https://news.google.com/rss/articles/CBMiX0FVX3lxTE5ZbXg3RWZ1RldrS3NoaFZWYXN2NEtUcHRGUll0dXhhQTBhNUZHTE9fLWQwRmRCTE0zTVZocGV0UTZ1M1BtQ3FKTlJfRWJoeFREOURWb1ZEQ3ZJZHNlelBv?oc=5\" target=\"_blank\"",
  "ai_analysis": {
    "relevance": "high",
    "summary": "電子書籍市場拡大、紙媒体衰退。コミック市場全体は成長も構造変化。",
    "true_intent": "電子書籍プラットフォームの優位性を示し、更なる市場拡大を狙う。紙媒体衰退を強調し、電子書籍への移行を促す狙いも。出版社側のデジタルシフト戦略の正当化。",
    "bias_warning": "あり",
    "deadline": null,
    "company": null,
    "action_required": true,
    "category": "出版/メディア/IT",
    "target_year": "2027"
  },
  "critical_analysis": {
    "true_intent": "電子書籍プラットフォームの優位性を示し、更なる市場拡大を狙う。紙媒体衰退を強調し、電子書籍への移行を促す狙いも。出版社側のデジタルシフト戦略の正当化。",
    "bias_warning": "あり"
  },
  "collected_at": "2026-01-27T16:41:11.941494",
  "source": "Active:小学館"
}