{
  "title": "三井住友信託銀行代表取締役社長・大山一也 さんの本棚 読書で暗黙知や潜在意識を耕す - 好書好日",
  "link": "https://news.google.com/rss/articles/CBMiUEFVX3lxTFBZUVUwTkl0TDJBNVRjOUFxbExEdWN3cW9BbGRWRkR1TTBIblVkTnF5SmpDRFVjbC1qNTgyaGpxeTlMSXZVNjBLc2lKX3BCblM3?oc=5",
  "raw_summary": "<a href=\"https://news.google.com/rss/articles/CBMiUEFVX3lxTFBZUVUwTkl0TDJBNVRjOUFxbExEdWN3cW9BbGRWRkR1TTBIblVkTnF5SmpDRFVjbC1qNTgyaGpxeTlMSXZVNjBLc2lKX3BCblM3?oc=5\" target=\"_blank\">三井住友信託銀行代表取締役社長・大山一也 さんの本棚 読書で暗黙知や潜在意識を耕す</a>&nbsp;&nbsp;<font color=\"#6f6f6f\">好書好日</font>",
  "ai_analysis": {
    "strength": "トップの知的好奇心の高さ、読書を通じた自己啓発を重視する企業文化、変化への適応力、知的資本の蓄積",
    "weakness": "トップダウン色が強い可能性、社員の自主性や多様性の軽視、読書偏重の可能性（他のスキルや経験の軽視）、形式主義に陥るリスク",
    "opportunity": "企業文化やトップの考え方を深く理解するチャンス、選考で読書体験や知識を活かすチャンス、企業が求める人物像（知的好奇心旺盛な人材）を把握するチャンス",
    "threat": "金融業界全体のデジタル化の遅れ、異業種からの参入、読書離れによる社員のスキル不足、情報過多による意思決定の遅延"
  },
  "critical_analysis": {},
  "deep_strategic_dossier": "",
  "bias": "",
  "collected_at": "2026-01-28T16:30:53.676736",
  "source": "Active:ポスト構造主義",
  "score": 5
}