{
  "title": "トヨタ社長が認めた「中国の超進化」：佐藤恒治氏が断行する「信頼と権限委譲」の経営改革 - note",
  "link": "https://news.google.com/rss/articles/CBMiVEFVX3lxTFBNWm8yV3EtWFVRYnVBT2VZVV9DV25FSG5CWVBweTlXTDgtc1VDaTVqRDF2MFdud2Jadmw0QW9YaERxSlZROTdQeUJHTFJfa2g3anRWeA?oc=5",
  "raw_summary": "<a href=\"https://news.google.com/rss/articles/CBMiVEFVX3lxTFBNWm8yV3EtWFVRYnVBT2VZVV9DV25FSG5CWVBweTlXTDgtc1VDaTVqRDF2MFdud2Jadmw0QW9YaERxSlZROTdQeUJHTFJfa2g3anRWeA?oc=5\" target=\"_blank\">トヨタ社長が認めた「中国の超進化」：佐藤恒治氏が断行する「信頼と権限委譲」の経営改革</a>&nbsp;&nbsp;<font color=\"#6f6f6f\">note</font>",
  "ai_analysis": {
    "strength": "中国市場への適応力強化、意思決定の迅速化、現地主導によるイノベーション促進。",
    "weakness": "本社からのコントロール低下、品質管理のばらつき、現地スタッフへの過度な負担、グローバルでのブランドイメージの一貫性維持の難しさ。",
    "opportunity": "グローバルビジネス、特に中国市場におけるビジネス戦略の立案・実行に携わるチャンス。組織変革期におけるリーダーシップの発揮。",
    "threat": "中国市場における競争激化、技術革新のスピード、地政学的リスク、サプライチェーンの脆弱性。"
  },
  "critical_analysis": {},
  "deep_strategic_dossier": "",
  "bias": "",
  "collected_at": "2026-01-28T12:52:57.748972",
  "source": "Active:トヨタ自動車",
  "score": 5
}