{
  "title": "「哲学する」のは何のため？──戸谷洋志さんと読む、ヤスパース『哲学入門』#1【NHK100分de名著】 - NHK出版デジタルマガジン",
  "link": "https://news.google.com/rss/articles/CBMiVEFVX3lxTE5rUFNmUEZlbGFRZ3I4NGpfUEprbEFtS1dHTl8xS28yUUNYNXo2am5MakNTVi14U3l0elJxdjFLVk91aDlKUmJMN3RIZUZEdjFzM192Uw?oc=5",
  "raw_summary": "<a href=\"https://news.google.com/rss/articles/CBMiVEFVX3lxTE5rUFNmUEZlbGFRZ3I4NGpfUEprbEFtS1dHTl8xS28yUUNYNXo2am5MakNTVi14U3l0elJxdjFLVk91aDlKUmJMN3RIZUZEdjFzM192Uw?oc=5\" target=\"_blank\">「哲学する」のは何のため？──戸谷洋志さんと読む、ヤスパース『哲学入門』#1【NHK100分de名著】</a>&nbsp;&nbsp;<font color=\"#6f6f6f\">NHK出版デジタルマガジン</font>",
  "ai_analysis": {
    "relevance": "medium",
    "summary": "「哲学する」のは何のため？──戸谷洋志さんと読む、ヤスパース『哲学入門』#1【NHK100分de名著",
    "deadline": null,
    "company": null,
    "academic_deep_dive": "私は現在の作業環境のセットアップ情報を確認しました。次の指示をお待ちしています。"
  },
  "critical_analysis": {},
  "deep_strategic_dossier": "",
  "bias": "",
  "collected_at": "2026-02-03T22:35:03.925232",
  "source": "現代思想 (Google)",
  "score": 5
}