{
  "title": "Careers News & Events - 2025年02月20日 2026年4月入社新卒採用エントリー・説明会情報 - Sony Honda Mobility Afeela",
  "link": "https://news.google.com/rss/articles/CBMibkFVX3lxTE45Z1p4YkJjYVFJWVYyeWNqRnBQYlJ5dHdrYjJ3SHIydW9MaVlsMWFubnJ0Y19pcGMwM2JfMVcta1VBZTZPTmd0R3paYi1OUWdKckc2eTJKekJPUU41eGlMOTBtZTJiek9ESWtXdFFB?oc=5",
  "raw_summary": "<a href=\"https://news.google.com/rss/articles/CBMibkFVX3lxTE45Z1p4YkJjYVFJWVYyeWNqRnBQYlJ5dHdrYjJ3SHIydW9MaVlsMWFubnJ0Y19pcGMwM2JfMVcta1VBZTZPTmd0R3paYi1OUWdKckc2eTJKekJPUU41eGlMOTBtZTJiek9ESWtXdFFB?oc=5\" target=\"_blank\">Careers News & Events - 2025年02月20日 2026年4月入社新卒採用エントリー・説明会情報</a>&nbsp;&nbsp;<font color=\"#6f6f6f\">Sony Honda Mobility Afeela</font>",
  "ai_analysis": {
    "strength": "ソニーとホンダという異業種大手2社の技術力とブランド力を背景に持つ。革新的なモビリティ開発への期待が高い。新しい企業文化を創り上げられる自由度。",
    "weakness": "新規合弁会社であるため、組織体制や意思決定プロセスが確立されていない可能性がある。両社の企業文化の融合に課題が残る可能性。実績がまだないため、リスクを嫌う層には敬遠される可能性。",
    "opportunity": "既存の自動車業界の枠にとらわれない、新しい価値創造に貢献できる。初期メンバーとして、企業の成長を牽引できるチャンス。異業種融合の最前線で、多様なスキルを習得できる。",
    "threat": "自動車業界の技術革新のスピードが速く、競争が激化している。既存の自動車メーカーとの顧客獲得競争は厳しい。法規制や安全基準の変化に迅速に対応する必要がある。"
  },
  "critical_analysis": {},
  "deep_strategic_dossier": "",
  "bias": "",
  "collected_at": "2026-01-28T13:15:45.422472",
  "source": "ソニーグループ 戦略",
  "score": 5
}