{
  "title": "【イベントのお知らせ】2025年8月28日（木）HR Craft Night vol.33開催決定「新卒採用、サマーインターンを振り返るの会」 - ユナイテッド株式会社",
  "link": "https://news.google.com/rss/articles/CBMiWkFVX3lxTE9MMlEwT2tsMlVfSmhMQTlIRnhVM01TSEszZ19jSnE4U0ZxcHoyaXRaZmZDMm4tZTJDRWtKRno1Q05MTHVpOGU4d0ZoR09JQmhUYTF4X0pPT2RCQQ?oc=5",
  "raw_summary": "<a href=\"https://news.google.com/rss/articles/CBMiWkFVX3lxTE9MMlEwT2tsMlVfSmhMQTlIRnhVM01TSEszZ19jSnE4U0ZxcHoyaXRaZmZDMm4tZTJDRWtKRno1Q05MTHVpOGU4d0ZoR09JQmhUYTF4X0pPT2RCQQ?oc=5\" target=\"_blank\">【イベントのお知らせ】2025年8月28日（木）HR Craft Night vol.33開催決定「新卒採用、サマーインターンを振り返るの会」</a>&nbsp;&nbsp;<font color=\"#6f6f6f\">ユナイテッド株式会社</font>",
  "ai_analysis": {
    "relevance": "medium",
    "summary": "【イベントのお知らせ】2025年8月28日（木）HR Craft Night vol.33開催決定「",
    "deadline": null,
    "company": null
  },
  "critical_analysis": {},
  "deep_strategic_dossier": "",
  "bias": "",
  "collected_at": "2026-02-01T09:18:45.966093",
  "source": "Active:サイバーエージェント",
  "score": 5
}