{
  "title": "進む早期化。「本選考を受けた」が早くも6割を超える - PR TIMES",
  "link": "https://news.google.com/rss/articles/CBMiakFVX3lxTE5TaGF2dTUzelUxQ1A2dENvczVNMHZNNnRJTEJkWHFLWXVfVkdySjFBUi13LVFNZFA1WE5MdkkyVW9XYXlnWE9SNEdaQ3NkZTlfclBlejFUTE9kczYtWXpMS1B2RWtFTDk0bmc?oc=5",
  "raw_summary": "<a href=\"https://news.google.com/rss/articles/CBMiakFVX3lxTE5TaGF2dTUzelUxQ1A2dENvczVNMHZNNnRJTEJkWHFLWXVfVkdySjFBUi13LVFNZFA1WE5MdkkyVW9XYXlnWE9SNEdaQ3NkZTlfclBlejFUTE9kczYtWXpMS1B2RWtFTDk0bmc?oc=5\" target=\"_blank\">進む早期化。「本選考を受けた」が早くも6割を超える</a>&nbsp;&nbsp;<font color=\"#6f6f6f\">PR TIMES</font>",
  "ai_analysis": {
    "strength": "早期選考を実施できる企業は、採用活動にリソースを割ける体力がある。ブランド力や将来性への自信の表れとも言える。",
    "weakness": "早期選考は、企業理解が浅い学生を多く選考する可能性があり、ミスマッチのリスクが高い。内定辞退率の上昇や、早期離職につながる可能性も孕む。",
    "opportunity": "準備を万全にした学生にとっては、競争率が比較的低い早期選考で内定を得るチャンス。インターンシップ等で企業理解を深め、早期選考に臨むことが重要。",
    "threat": "就活時期の長期化により、学業への影響や学生の精神的な負担が増大する可能性がある。企業側も、選考期間の長期化による採用コストの増大が懸念される。"
  },
  "critical_analysis": {},
  "deep_strategic_dossier": "",
  "bias": "",
  "collected_at": "2026-01-28T13:03:32.277139",
  "source": "就活ニュース (Google)",
  "score": 5
}