{
  "title": "ニデックのEVモーター「99％中国製」で価格競争を勝ち抜く－",
  "link": "https://news.google.com/rss/articles/CBMiZ0FVX3lxTFBQbjB6eGozb01DSjl5M1VZT2V6YS1qSXpnYmx1SDFlSEJ1ZTRIUWJWZWxuQjdXRkE1N1JoNDFRdVdJOFp1MEgzWEdzQThnTVoycTgyLTBLd3RfU2JJeUQ2dUpWU3JOdUk?oc=5",
  "raw_summary": "<a href=\"https://news.google.com/rss/articles/CBMiZ0FVX3lxTFBQbjB6eGozb01DSjl5M1VZT2V6YS1qSXpnYmx1SDFlSEJ1ZTRIUWJWZWxuQjdXRkE1N1JoNDFRdVdJOFp1MEgzWEdzQThnTVoycTgyLTBLd3RfU2JJeUQ2dUpWU3JOdUk?oc=5\" targ",
  "ai_analysis": {
    "relevance": "high",
    "summary": "このニュースは、ニデックのEVモーターが99％中国製であることを指摘しているため、中国への依存度や競争力の低下に関する懸念を raisedしている可能性があります",
    "true_intent": "この情報の裏にある意図は、中国への依存度や競争力の低下を懸念させるための情報である可能性があります",
    "bias_warning": "この情報は、 China との経済関係や競争力の比較を分析するための情報として、適切な分析方法が用いる可能性があります",
    "deadline": null,
    "company": null,
    "action_required": true,
    "category": "政治",
    "target_year": "2027"
  },
  "critical_analysis": {
    "true_intent": "この情報の裏にある意図は、中国への依存度や競争力の低下を懸念させるための情報である可能性があります",
    "bias_warning": "この情報は、 China との経済関係や競争力の比較を分析するための情報として、適切な分析方法が用いる可能性があります"
  },
  "collected_at": "2026-01-26T17:58:05.365051",
  "source": "トヨタ自動車 戦略"
}