{
  "title": "プレスリリース：Nint、ECの利益が残らない構造課題に挑む「利益基準のEC経営」共催セミナーを開催（PR TIMES） - 毎日新聞",
  "link": "https://news.google.com/rss/articles/CBMiaEFVX3lxTE5VMlNKdlZ2LWVoU3dianNWdndIbnBDNHdzZVExS1o5XzV2a2pUSkNkbTBISzNZY3R1N3g0c0lOMFN0RkxWM3VIUVFpM1gxb1UzeEJ3MnphbG1OWUVxMjVxLW1WalhIOXdZ?oc=5",
  "raw_summary": "<a href=\"https://news.google.com/rss/articles/CBMiaEFVX3lxTE5VMlNKdlZ2LWVoU3dianNWdndIbnBDNHdzZVExS1o5XzV2a2pUSkNkbTBISzNZY3R1N3g0c0lOMFN0RkxWM3VIUVFpM1gxb1UzeEJ3MnphbG1OWUVxMjVxLW1WalhIOXdZ?oc=5\" target=\"_blank\">プレスリリース：Nint、ECの利益が残らない構造課題に挑む「利益基準のEC経営」共催セミナーを開催（PR TIMES）</a>&nbsp;&nbsp;<font color=\"#6f6f6f\">毎日新聞</font>",
  "ai_analysis": {
    "strength": "ECデータ分析における専門性と実績、セミナー開催による情報発信力、パートナー企業との連携。",
    "weakness": "セミナー参加者以外への情報リーチの限界、データ分析サービスの高価格帯による導入障壁、競合他社との差別化。",
    "opportunity": "EC業界の構造的課題に対する深い理解を示すことで、データ分析スキルやECコンサルティング能力をアピールできる。Nintのようなデータ分析企業への就職は、今後も成長が見込める。",
    "threat": "ECプラットフォーム側の機能強化によるデータ分析ニーズの低下、個人情報保護規制の強化によるデータ収集の制限、AIによる自動分析ツールの普及。"
  },
  "critical_analysis": {},
  "deep_strategic_dossier": "",
  "bias": "",
  "collected_at": "2026-01-28T15:58:52.588363",
  "source": "Active:ポスト構造主義",
  "score": 5
}