{
  "title": "ローソン、KDDIとフィリピンでAI活用実験、店舗運営効率化と売上向上を検証 - ダイヤモンド・チェーンストアオンライン",
  "link": "https://news.google.com/rss/articles/CBMiU0FVX3lxTE5aNXVTSTFqbVg1Tkk5ZEl2RGFhMG4yeXZrNG53RlR4eTBZelpLZHd6dmpIYjczNUdNUWVINk9JYXptOHhmUk8tOW95X3lxSlIyMGtB?oc=5",
  "raw_summary": "<a href=\"https://news.google.com/rss/articles/CBMiU0FVX3lxTE5aNXVTSTFqbVg1Tkk5ZEl2RGFhMG4yeXZrNG53RlR4eTBZelpLZHd6dmpIYjczNUdNUWVINk9JYXptOHhmUk8tOW95X3lxSlIyMGtB?oc=5\" target=\"_blank\">ローソン、KDDIとフィリピンでAI活用実験、店舗運営効率化と売上向上を検証</a>&nbsp;&nbsp;<font color=\"#6f6f6f\">ダイヤモンド・チェーンストアオンライン</font>",
  "ai_analysis": {
    "relevance": "medium",
    "summary": "ローソン、KDDIとフィリピンでAI活用実験、店舗運営効率化と売上向上を検証 - ダイヤモンド・チェ",
    "deadline": null,
    "company": null
  },
  "critical_analysis": {},
  "deep_strategic_dossier": "",
  "bias": "",
  "collected_at": "2026-02-02T02:50:09.553878",
  "source": "Lawson KDDI Strategy",
  "score": 5
}